xpibee
