Metadata-Version: 1.0
Name: xpibee
Version: 0.1.37
Summary: Send commands via an XBee 2 (ZB)
Home-page: https://github.com/sachinio/pilibs/tree/master/src/xpibee
Author: Sachin Patney
Author-email: UNKNOWN
License: MIT
Platform: UNKNOWN
